README.md
setup.py
clever_client/__init__.py
clever_client/api_client.py
clever_client/configuration.py
clever_client/rest.py
clever_client/api/__init__.py
clever_client/api/courses_api.py
clever_client/api/districts_api.py
clever_client/api/events_api.py
clever_client/api/resources_api.py
clever_client/api/schools_api.py
clever_client/api/sections_api.py
clever_client/api/terms_api.py
clever_client/api/users_api.py
clever_client/models/__init__.py
clever_client/models/bad_request.py
clever_client/models/contact.py
clever_client/models/course.py
clever_client/models/course_object.py
clever_client/models/course_response.py
clever_client/models/courses_created.py
clever_client/models/courses_deleted.py
clever_client/models/courses_response.py
clever_client/models/courses_updated.py
clever_client/models/credentials.py
clever_client/models/district.py
clever_client/models/district_admin.py
clever_client/models/district_contact.py
clever_client/models/district_object.py
clever_client/models/district_response.py
clever_client/models/districts_created.py
clever_client/models/districts_deleted.py
clever_client/models/districts_response.py
clever_client/models/districts_updated.py
clever_client/models/event.py
clever_client/models/event_response.py
clever_client/models/event_response_with_uri.py
clever_client/models/events_response.py
clever_client/models/internal_error.py
clever_client/models/link.py
clever_client/models/location.py
clever_client/models/name.py
clever_client/models/not_found.py
clever_client/models/principal.py
clever_client/models/resource.py
clever_client/models/resource_object.py
clever_client/models/resource_response.py
clever_client/models/resources_created.py
clever_client/models/resources_deleted.py
clever_client/models/resources_response.py
clever_client/models/resources_updated.py
clever_client/models/roles.py
clever_client/models/school.py
clever_client/models/school_enrollment.py
clever_client/models/school_object.py
strongmind_clever_client.egg-info/PKG-INFO
strongmind_clever_client.egg-info/SOURCES.txt
strongmind_clever_client.egg-info/dependency_links.txt
strongmind_clever_client.egg-info/requires.txt
strongmind_clever_client.egg-info/top_level.txt
